logtail/__init__.py
logtail/compat.py
logtail/flusher.py
logtail/formatter.py
logtail/frame.py
logtail/handler.py
logtail/helpers.py
logtail/uploader.py
logtail_python-0.3.2.dist-info/LICENSE.md
logtail_python-0.3.2.dist-info/METADATA
logtail_python-0.3.2.dist-info/WHEEL
logtail_python-0.3.2.dist-info/top_level.txt
logtail_python-0.3.2.dist-info/RECORD
