Metadata-Version: 2.1
Name: logtail-python
Version: 0.3.2
Summary: Logtail.com client library
Home-page: https://github.com/logtail/logtail-python
Download-URL: https://github.com/logtail/logtail-python/tarball/0.3.2
Author: Logtail
Author-email: hello@logtail.com
License: ISC
Keywords: api,logtail,logging,client
Classifier: Intended Audience :: Developers
Classifier: License :: OSI Approved :: ISC License (ISCL)
Classifier: Operating System :: OS Independent
Classifier: Programming Language :: Python :: 3
Classifier: Programming Language :: Python :: 3.7
Classifier: Programming Language :: Python :: 3.8
Classifier: Programming Language :: Python :: 3.9
Classifier: Programming Language :: Python :: 3.10
Classifier: Programming Language :: Python :: 3.11
Classifier: Programming Language :: Python
Classifier: Topic :: Software Development :: Libraries :: Python Modules
License-File: LICENSE.md
Requires-Dist: requests>=2.18.4
Requires-Dist: msgpack>=0.5.6
